{"rewards": [{"monsterId": 33, "monsterName": "Кирин", "rank": "MR", "condition": "Guiding Lands (Tempered)", "stack": 1, "percentage": 35}, {"monsterId": 44, "monsterName": "Теостра", "rank": "MR", "condition": "Guiding Lands (Tempered)", "stack": 1, "percentage": 33}, {"monsterId": 49, "monsterName": "Лунастра", "rank": "MR", "condition": "Guiding Lands (Tempered)", "stack": 1, "percentage": 33}, {"monsterId": 45, "monsterName": "Кушала-даора", "rank": "MR", "condition": "Guiding Lands (Tempered)", "stack": 1, "percentage": 33}, {"monsterId": 125, "monsterName": "Велхана", "rank": "MR", "condition": "Guiding Lands (Tempered)", "stack": 1, "percentage": 33}, {"monsterId": 127, "monsterName": "Тленный ваал-хазак", "rank": "MR", "condition": "Guiding Lands (Tempered)", "stack": 1, "percentage": 33}, {"monsterId": 128, "monsterName": "Намиэль", "rank": "MR", "condition": "Guiding Lands (Tempered)", "stack": 1, "percentage": 33}, {"monsterId": 130, "monsterName": "Нергигант-губитель", "rank": "MR", "condition": "Guiding Lands (Tempered)", "stack": 1, "percentage": 33}], "gathering": [], "quests": []}