[{"id":277,"name":"Tigrex Bruto α+","rank":"MR","bonus":{"name":"Essência de Tigrex","description":null,"skills":[{"name":"Segredo Refeição Grátis","description":"Aumenta o nível máximo da habilidade Refeição Grátis.","required":3,"levels":[{"level":1,"description":"Aumenta o nível máximo da habilidade Refeição Grátis."}]}]},"pieces":[{"id":1237,"name":"Elmo Rugido Rex α+","type":"head","rarity":11,"defenseBase":158,"defenseMax":182,"defenseAugmentMax":202,"fire":3,"water":-4,"thunder":-2,"ice":0,"dragon":0,"slot1":3,"slot2":0,"slot3":0,"skills":[{"name":"Reforço de Ataque","description":"Aumenta o poder de ataque. Também aumenta a afinidade em níveis mais altos.","level":3,"levels":[{"level":1,"description":"Ataque +3"},{"level":2,"description":"Ataque +6"},{"level":3,"description":"Ataque +9"},{"level":4,"description":"Ataque +12 Afinidade +5%"},{"level":5,"description":"Ataque +15 Afinidade +5%"},{"level":6,"description":"Ataque +18 Afinidade +5%"},{"level":7,"description":"Ataque +21 Afinidade +5%"}]},{"name":"Refeição Grátis","description":"Concede uma chance predeterminada de consumir um alimento ou bebida gratuitamente.","level":1,"levels":[{"level":1,"description":"Ativa 25% do tempo."},{"level":2,"description":"Ativa 50% do tempo."},{"level":3,"description":"Ativa 75% do tempo."}]}],"materials":[{"itemId":889,"name":"Fragmento de Tigrex Bruto","quantity":2},{"itemId":890,"name":"Córtex de Tigrex Bruto","quantity":3},{"itemId":892,"name":"Presadura de Tigrex Bruto","quantity":2},{"itemId":1006,"name":"Cristal Distorcido","quantity":5}]},{"id":1238,"name":"Armadura Rugido Rex α+","type":"chest","rarity":11,"defenseBase":158,"defenseMax":182,"defenseAugmentMax":202,"fire":3,"water":-4,"thunder":-2,"ice":0,"dragon":0,"slot1":3,"slot2":0,"slot3":0,"skills":[{"name":"Reforço de Ataque","description":"Aumenta o poder de ataque. Também aumenta a afinidade em níveis mais altos.","level":3,"levels":[{"level":1,"description":"Ataque +3"},{"level":2,"description":"Ataque +6"},{"level":3,"description":"Ataque +9"},{"level":4,"description":"Ataque +12 Afinidade +5%"},{"level":5,"description":"Ataque +15 Afinidade +5%"},{"level":6,"description":"Ataque +18 Afinidade +5%"},{"level":7,"description":"Ataque +21 Afinidade +5%"}]},{"name":"Exploração de Fraqueza","description":"Aumenta a afinidade de ataques que exploram o ponto fraco do monstro.","level":1,"levels":[{"level":1,"description":"Ataques que atingem pontos fracos têm mais 10% de afinidade e 5% extras em partes feridas."},{"level":2,"description":"Ataques que atingem pontos fracos têm mais 15% de afinidade e 15% extras em partes feridas."},{"level":3,"description":"Ataques que atingem pontos fracos têm mais 30% de afinidade e 20% extras em partes feridas."}]}],"materials":[{"itemId":889,"name":"Fragmento de Tigrex Bruto","quantity":2},{"itemId":890,"name":"Córtex de Tigrex Bruto","quantity":3},{"itemId":892,"name":"Presadura de Tigrex Bruto","quantity":3},{"itemId":1020,"name":"Furiosso Enfermo","quantity":3}]},{"id":1239,"name":"Braçad. Rugido Rex α+","type":"arms","rarity":11,"defenseBase":158,"defenseMax":182,"defenseAugmentMax":202,"fire":3,"water":-4,"thunder":-2,"ice":0,"dragon":0,"slot1":3,"slot2":0,"slot3":0,"skills":[{"name":"Reforço de Vida","description":"Aumenta a vida.","level":3,"levels":[{"level":1,"description":"Vida +15"},{"level":2,"description":"Vida +30"},{"level":3,"description":"Vida +50"}]},{"name":"Reforço de Ataque","description":"Aumenta o poder de ataque. Também aumenta a afinidade em níveis mais altos.","level":2,"levels":[{"level":1,"description":"Ataque +3"},{"level":2,"description":"Ataque +6"},{"level":3,"description":"Ataque +9"},{"level":4,"description":"Ataque +12 Afinidade +5%"},{"level":5,"description":"Ataque +15 Afinidade +5%"},{"level":6,"description":"Ataque +18 Afinidade +5%"},{"level":7,"description":"Ataque +21 Afinidade +5%"}]}],"materials":[{"itemId":889,"name":"Fragmento de Tigrex Bruto","quantity":2},{"itemId":890,"name":"Córtex de Tigrex Bruto","quantity":3},{"itemId":891,"name":"Garrígida de Tigrex Bruto","quantity":2},{"itemId":1018,"name":"Furiosso Deformado","quantity":3}]},{"id":1240,"name":"Cinturão Rugido Rex α+","type":"waist","rarity":11,"defenseBase":158,"defenseMax":182,"defenseAugmentMax":202,"fire":3,"water":-4,"thunder":-2,"ice":0,"dragon":0,"slot1":2,"slot2":0,"slot3":0,"skills":[{"name":"Aumento de Regeneração","description":"Aumenta a quantidade recuperada ao regenerar a vida.","level":3,"levels":[{"level":1,"description":"Regeneração +10%"},{"level":2,"description":"Regeneração +20%"},{"level":3,"description":"Regeneração +30%"}]},{"name":"Exploração de Fraqueza","description":"Aumenta a afinidade de ataques que exploram o ponto fraco do monstro.","level":1,"levels":[{"level":1,"description":"Ataques que atingem pontos fracos têm mais 10% de afinidade e 5% extras em partes feridas."},{"level":2,"description":"Ataques que atingem pontos fracos têm mais 15% de afinidade e 15% extras em partes feridas."},{"level":3,"description":"Ataques que atingem pontos fracos têm mais 30% de afinidade e 20% extras em partes feridas."}]}],"materials":[{"itemId":885,"name":"Relho de Tigrex","quantity":1},{"itemId":890,"name":"Córtex de Tigrex Bruto","quantity":3},{"itemId":891,"name":"Garrígida de Tigrex Bruto","quantity":3},{"itemId":1008,"name":"Cristal Crepuscular","quantity":3}]},{"id":1241,"name":"Grevas Rugido Rex α+","type":"legs","rarity":11,"defenseBase":158,"defenseMax":182,"defenseAugmentMax":202,"fire":3,"water":-4,"thunder":-2,"ice":0,"dragon":0,"slot1":1,"slot2":0,"slot3":0,"skills":[{"name":"Agitador","description":"Aumenta o poder de ataque e a afinidade quando monstros grandes se enfurecem.","level":3,"levels":[{"level":1,"description":"Ativado, concede ataque +4 e aumenta a afinidade em 5%."},{"level":2,"description":"Ativado, concede ataque +8 e aumenta a afinidade em 5%."},{"level":3,"description":"Ativado, concede ataque +12 e aumenta a afinidade em 7%."},{"level":4,"description":"Ativado, concede ataque +16 e aumenta a afinidade em 7%."},{"level":5,"description":"Ativado, concede ataque +20 e aumenta a afinidade em 10%."},{"level":6,"description":"Ativado, concede ataque +24 e aumenta a afinidade em 15%."},{"level":7,"description":"Ativado, concede ataque +28 e aumenta a afinidade em 20%."}]},{"name":"Exploração de Fraqueza","description":"Aumenta a afinidade de ataques que exploram o ponto fraco do monstro.","level":1,"levels":[{"level":1,"description":"Ataques que atingem pontos fracos têm mais 10% de afinidade e 5% extras em partes feridas."},{"level":2,"description":"Ataques que atingem pontos fracos têm mais 15% de afinidade e 15% extras em partes feridas."},{"level":3,"description":"Ataques que atingem pontos fracos têm mais 30% de afinidade e 20% extras em partes feridas."}]}],"materials":[{"itemId":888,"name":"Manto de Tigrex","quantity":1},{"itemId":890,"name":"Córtex de Tigrex Bruto","quantity":3},{"itemId":891,"name":"Garrígida de Tigrex Bruto","quantity":2},{"itemId":892,"name":"Presadura de Tigrex Bruto","quantity":2}]}]},{"id":278,"name":"Tigrex Bruto β+","rank":"MR","bonus":{"name":"Essência de Tigrex","description":null,"skills":[{"name":"Segredo Refeição Grátis","description":"Aumenta o nível máximo da habilidade Refeição Grátis.","required":3,"levels":[{"level":1,"description":"Aumenta o nível máximo da habilidade Refeição Grátis."}]}]},"pieces":[{"id":1242,"name":"Elmo Rugido Rex β+","type":"head","rarity":11,"defenseBase":158,"defenseMax":182,"defenseAugmentMax":202,"fire":3,"water":-4,"thunder":-2,"ice":0,"dragon":0,"slot1":4,"slot2":0,"slot3":0,"skills":[{"name":"Reforço de Ataque","description":"Aumenta o poder de ataque. Também aumenta a afinidade em níveis mais altos.","level":2,"levels":[{"level":1,"description":"Ataque +3"},{"level":2,"description":"Ataque +6"},{"level":3,"description":"Ataque +9"},{"level":4,"description":"Ataque +12 Afinidade +5%"},{"level":5,"description":"Ataque +15 Afinidade +5%"},{"level":6,"description":"Ataque +18 Afinidade +5%"},{"level":7,"description":"Ataque +21 Afinidade +5%"}]},{"name":"Refeição Grátis","description":"Concede uma chance predeterminada de consumir um alimento ou bebida gratuitamente.","level":1,"levels":[{"level":1,"description":"Ativa 25% do tempo."},{"level":2,"description":"Ativa 50% do tempo."},{"level":3,"description":"Ativa 75% do tempo."}]}],"materials":[{"itemId":889,"name":"Fragmento de Tigrex Bruto","quantity":2},{"itemId":890,"name":"Córtex de Tigrex Bruto","quantity":3},{"itemId":892,"name":"Presadura de Tigrex Bruto","quantity":2},{"itemId":1006,"name":"Cristal Distorcido","quantity":5}]},{"id":1243,"name":"Armadura Rugido Rex β+","type":"chest","rarity":11,"defenseBase":158,"defenseMax":182,"defenseAugmentMax":202,"fire":3,"water":-4,"thunder":-2,"ice":0,"dragon":0,"slot1":4,"slot2":1,"slot3":0,"skills":[{"name":"Reforço de Ataque","description":"Aumenta o poder de ataque. Também aumenta a afinidade em níveis mais altos.","level":2,"levels":[{"level":1,"description":"Ataque +3"},{"level":2,"description":"Ataque +6"},{"level":3,"description":"Ataque +9"},{"level":4,"description":"Ataque +12 Afinidade +5%"},{"level":5,"description":"Ataque +15 Afinidade +5%"},{"level":6,"description":"Ataque +18 Afinidade +5%"},{"level":7,"description":"Ataque +21 Afinidade +5%"}]},{"name":"Exploração de Fraqueza","description":"Aumenta a afinidade de ataques que exploram o ponto fraco do monstro.","level":1,"levels":[{"level":1,"description":"Ataques que atingem pontos fracos têm mais 10% de afinidade e 5% extras em partes feridas."},{"level":2,"description":"Ataques que atingem pontos fracos têm mais 15% de afinidade e 15% extras em partes feridas."},{"level":3,"description":"Ataques que atingem pontos fracos têm mais 30% de afinidade e 20% extras em partes feridas."}]}],"materials":[{"itemId":889,"name":"Fragmento de Tigrex Bruto","quantity":2},{"itemId":890,"name":"Córtex de Tigrex Bruto","quantity":3},{"itemId":892,"name":"Presadura de Tigrex Bruto","quantity":3},{"itemId":1020,"name":"Furiosso Enfermo","quantity":3}]},{"id":1244,"name":"Braçad. Rugido Rex β+","type":"arms","rarity":11,"defenseBase":158,"defenseMax":182,"defenseAugmentMax":202,"fire":3,"water":-4,"thunder":-2,"ice":0,"dragon":0,"slot1":4,"slot2":0,"slot3":0,"skills":[{"name":"Reforço de Vida","description":"Aumenta a vida.","level":2,"levels":[{"level":1,"description":"Vida +15"},{"level":2,"description":"Vida +30"},{"level":3,"description":"Vida +50"}]},{"name":"Reforço de Ataque","description":"Aumenta o poder de ataque. Também aumenta a afinidade em níveis mais altos.","level":2,"levels":[{"level":1,"description":"Ataque +3"},{"level":2,"description":"Ataque +6"},{"level":3,"description":"Ataque +9"},{"level":4,"description":"Ataque +12 Afinidade +5%"},{"level":5,"description":"Ataque +15 Afinidade +5%"},{"level":6,"description":"Ataque +18 Afinidade +5%"},{"level":7,"description":"Ataque +21 Afinidade +5%"}]}],"materials":[{"itemId":889,"name":"Fragmento de Tigrex Bruto","quantity":2},{"itemId":890,"name":"Córtex de Tigrex Bruto","quantity":3},{"itemId":891,"name":"Garrígida de Tigrex Bruto","quantity":2},{"itemId":1018,"name":"Furiosso Deformado","quantity":3}]},{"id":1245,"name":"Cinturão Rugido Rex β+","type":"waist","rarity":11,"defenseBase":158,"defenseMax":182,"defenseAugmentMax":202,"fire":3,"water":-4,"thunder":-2,"ice":0,"dragon":0,"slot1":4,"slot2":0,"slot3":0,"skills":[{"name":"Aumento de Regeneração","description":"Aumenta a quantidade recuperada ao regenerar a vida.","level":2,"levels":[{"level":1,"description":"Regeneração +10%"},{"level":2,"description":"Regeneração +20%"},{"level":3,"description":"Regeneração +30%"}]},{"name":"Exploração de Fraqueza","description":"Aumenta a afinidade de ataques que exploram o ponto fraco do monstro.","level":1,"levels":[{"level":1,"description":"Ataques que atingem pontos fracos têm mais 10% de afinidade e 5% extras em partes feridas."},{"level":2,"description":"Ataques que atingem pontos fracos têm mais 15% de afinidade e 15% extras em partes feridas."},{"level":3,"description":"Ataques que atingem pontos fracos têm mais 30% de afinidade e 20% extras em partes feridas."}]}],"materials":[{"itemId":885,"name":"Relho de Tigrex","quantity":1},{"itemId":890,"name":"Córtex de Tigrex Bruto","quantity":3},{"itemId":891,"name":"Garrígida de Tigrex Bruto","quantity":3},{"itemId":1008,"name":"Cristal Crepuscular","quantity":3}]},{"id":1246,"name":"Grevas Rugido Rex β+","type":"legs","rarity":11,"defenseBase":158,"defenseMax":182,"defenseAugmentMax":202,"fire":3,"water":-4,"thunder":-2,"ice":0,"dragon":0,"slot1":4,"slot2":0,"slot3":0,"skills":[{"name":"Agitador","description":"Aumenta o poder de ataque e a afinidade quando monstros grandes se enfurecem.","level":2,"levels":[{"level":1,"description":"Ativado, concede ataque +4 e aumenta a afinidade em 5%."},{"level":2,"description":"Ativado, concede ataque +8 e aumenta a afinidade em 5%."},{"level":3,"description":"Ativado, concede ataque +12 e aumenta a afinidade em 7%."},{"level":4,"description":"Ativado, concede ataque +16 e aumenta a afinidade em 7%."},{"level":5,"description":"Ativado, concede ataque +20 e aumenta a afinidade em 10%."},{"level":6,"description":"Ativado, concede ataque +24 e aumenta a afinidade em 15%."},{"level":7,"description":"Ativado, concede ataque +28 e aumenta a afinidade em 20%."}]},{"name":"Exploração de Fraqueza","description":"Aumenta a afinidade de ataques que exploram o ponto fraco do monstro.","level":1,"levels":[{"level":1,"description":"Ataques que atingem pontos fracos têm mais 10% de afinidade e 5% extras em partes feridas."},{"level":2,"description":"Ataques que atingem pontos fracos têm mais 15% de afinidade e 15% extras em partes feridas."},{"level":3,"description":"Ataques que atingem pontos fracos têm mais 30% de afinidade e 20% extras em partes feridas."}]}],"materials":[{"itemId":888,"name":"Manto de Tigrex","quantity":1},{"itemId":890,"name":"Córtex de Tigrex Bruto","quantity":3},{"itemId":891,"name":"Garrígida de Tigrex Bruto","quantity":2},{"itemId":892,"name":"Presadura de Tigrex Bruto","quantity":2}]}]}]