{"rewards": [{"monsterId": 23, "monsterName": "蠻顎龍", "rank": "MR", "condition": "Investigation (Gold)", "stack": 1, "percentage": 18}, {"monsterId": 23, "monsterName": "蠻顎龍", "rank": "MR", "condition": "Investigation (Silver)", "stack": 1, "percentage": 10}, {"monsterId": 23, "monsterName": "蠻顎龍", "rank": "MR", "condition": "Wound Head", "stack": 1, "percentage": 3}, {"monsterId": 23, "monsterName": "蠻顎龍", "rank": "MR", "condition": "Tail Carve", "stack": 1, "percentage": 3}, {"monsterId": 23, "monsterName": "蠻顎龍", "rank": "MR", "condition": "Carve / Capture", "stack": 1, "percentage": 2}, {"monsterId": 23, "monsterName": "蠻顎龍", "rank": "MR", "condition": "Plunderblade", "stack": 1, "percentage": 1}], "gathering": [], "quests": [{"questId": 66805, "questName": "真正的暴徒是哪個？！", "category": "event", "rank": "MR", "stars": 2, "rewardGroup": "A", "stack": 1, "percentage": 5}, {"questId": 66826, "questName": "大樹的約德爾", "category": "event", "rank": "MR", "stars": 6, "rewardGroup": "A", "stack": 1, "percentage": 5}]}