{"rewards":[],"gathering":[{"locationId":1,"locationName":"Ancient Forest","area":6,"rank":null,"stack":1,"percentage":100,"nodes":3},{"locationId":1,"locationName":"Ancient Forest","area":11,"rank":null,"stack":1,"percentage":100,"nodes":2},{"locationId":1,"locationName":"Ancient Forest","area":15,"rank":null,"stack":1,"percentage":100,"nodes":null},{"locationId":3,"locationName":"Coral Highlands","area":13,"rank":null,"stack":1,"percentage":100,"nodes":null},{"locationId":5,"locationName":"Elder's Recess","area":7,"rank":null,"stack":1,"percentage":100,"nodes":null},{"locationId":4,"locationName":"Rotten Vale","area":6,"rank":null,"stack":1,"percentage":100,"nodes":null},{"locationId":2,"locationName":"Wildspire Waste","area":3,"rank":null,"stack":1,"percentage":100,"nodes":null}],"quests":[],"combinations":{"produces":[],"usedIn":[{"type":"usedIn","resultName":"Poison Smoke Bomb","resultId":64,"first":"Smokenut","firstId":39,"second":"Toadstool","secondId":46,"quantity":1},{"type":"usedIn","resultName":"Poisoned Meat","resultId":67,"first":"Raw Meat","firstId":66,"second":"Toadstool","secondId":46,"quantity":1},{"type":"usedIn","resultName":"Poison Knife","resultId":648,"first":"Throwing Knife","firstId":647,"second":"Toadstool","secondId":46,"quantity":1},{"type":"usedIn","resultName":"Poison Coating","resultId":595,"first":"Empty Phial","firstId":114,"second":"Toadstool","secondId":46,"quantity":1},{"type":"usedIn","resultName":"Poison Ammo 1","resultId":579,"first":"Normal Ammo 1","firstId":559,"second":"Toadstool","secondId":46,"quantity":2}]}}