{"rewards":[{"monsterId":122,"monsterName":"アンジャナフ亜種","rank":"MR","condition":"Wound Head","stack":1,"percentage":35},{"monsterId":122,"monsterName":"アンジャナフ亜種","rank":"MR","condition":"Carve / Capture","stack":1,"percentage":21},{"monsterId":122,"monsterName":"アンジャナフ亜種","rank":"MR","condition":"調査特別報酬・金","stack":1,"percentage":21},{"monsterId":122,"monsterName":"アンジャナフ亜種","rank":"MR","condition":"調査特別報酬・銀","stack":1,"percentage":19},{"monsterId":122,"monsterName":"アンジャナフ亜種","rank":"MR","condition":"クエスト報酬／銅枠","stack":1,"percentage":15}],"gathering":[]}