{"rewards": [{"monsterId": 34, "monsterName": "Zorah Magdaros", "rank": "HR", "condition": "Hunt (Bronze)", "stack": 1, "percentage": 8}], "gathering": [], "quests": [{"questId": 62606, "questName": "Crépuscule éternel", "category": "event", "rank": "HR", "stars": 9, "rewardGroup": "A", "stack": 1, "percentage": 8}, {"questId": 62606, "questName": "Crépuscule éternel", "category": "event", "rank": "HR", "stars": 9, "rewardGroup": "B", "stack": 1, "percentage": 8}, {"questId": 504, "questName": "Une tâche colossale", "category": "assigned", "rank": "LR", "stars": 6, "rewardGroup": "A", "stack": 1, "percentage": 8}, {"questId": 641, "questName": "D'un Z qui veut dire Zorah", "category": "optional", "rank": "LR", "stars": 6, "rewardGroup": "A", "stack": 1, "percentage": 8}, {"questId": 62608, "questName": "Regard sur l'aube", "category": "event", "rank": "LR", "stars": 6, "rewardGroup": "A", "stack": 1, "percentage": 8}]}