[{"itemId":543,"itemName":"윤기나는 비늘","iconName":"Scale","iconColor":"Cyan","rank":"MR","source":"palico","condition":"Bandit Mantle","stack":1,"percentage":100},{"itemId":1266,"itemName":"요염한 맹독침","iconName":"Body","iconColor":"Orange","rank":"MR","source":"guidingLands","condition":"Guiding Lands (High)","stack":1,"percentage":100},{"itemId":754,"itemName":"비독룡의 맹독침","iconName":"Body","iconColor":"Orange","rank":"MR","source":"break","condition":"Wound Head","stack":1,"percentage":100},{"itemId":753,"itemName":"비독룡의 억센발톱","iconName":"Fang","iconColor":"Orange","rank":"MR","source":"break","condition":"Wound Forelegs","stack":1,"percentage":100},{"itemId":750,"itemName":"비독룡의 두툼비늘","iconName":"Scale","iconColor":"Orange","rank":"MR","source":"tracking","condition":"Track","stack":1,"percentage":100},{"itemId":751,"itemName":"비독룡의 두툼모피","iconName":"Hide","iconColor":"Orange","rank":"MR","source":"break","condition":"Wound Back","stack":1,"percentage":80},{"itemId":754,"itemName":"비독룡의 맹독침","iconName":"Body","iconColor":"Orange","rank":"MR","source":"break","condition":"Wound Tail","stack":1,"percentage":80},{"itemId":1066,"itemName":"태고의 구슬","iconName":"Feystone","iconColor":"Violet","rank":"MR","source":"questReward","condition":"Investigation (Purple)","stack":1,"percentage":70},{"itemId":1021,"itemName":"용맥의 강용골","iconName":"Bone","iconColor":"DarkRed","rank":"MR","source":"guidingLands","condition":"Guiding Lands (Low)","stack":1,"percentage":63},{"itemId":1266,"itemName":"요염한 맹독침","iconName":"Body","iconColor":"Orange","rank":"MR","source":"guidingLands","condition":"Guiding Lands (Mid)","stack":1,"percentage":63},{"itemId":1267,"itemName":"역전의 맹독침","iconName":"Body","iconColor":"Orange","rank":"MR","source":"guidingLands","condition":"Guiding Lands (Tempered)","stack":1,"percentage":54},{"itemId":750,"itemName":"비독룡의 두툼비늘","iconName":"Scale","iconColor":"Orange","rank":"MR","source":"shiny","condition":"Shiny Drop","stack":1,"percentage":50},{"itemId":750,"itemName":"비독룡의 두툼비늘","iconName":"Scale","iconColor":"Orange","rank":"MR","source":"palico","condition":"Plunderblade","stack":1,"percentage":41},{"itemId":1021,"itemName":"용맥의 강용골","iconName":"Bone","iconColor":"DarkRed","rank":"MR","source":"guidingLands","condition":"Guiding Lands (Mid)","stack":1,"percentage":37},{"itemId":1266,"itemName":"요염한 맹독침","iconName":"Body","iconColor":"Orange","rank":"MR","source":"guidingLands","condition":"Guiding Lands (Low)","stack":1,"percentage":37},{"itemId":751,"itemName":"비독룡의 두툼모피","iconName":"Hide","iconColor":"Orange","rank":"MR","source":"palico","condition":"Plunderblade","stack":1,"percentage":35},{"itemId":750,"itemName":"비독룡의 두툼비늘","iconName":"Scale","iconColor":"Orange","rank":"MR","source":"carve","condition":"Carve / Capture","stack":1,"percentage":30},{"itemId":1067,"itemName":"각인된 구슬","iconName":"Feystone","iconColor":"Green","rank":"MR","source":"questReward","condition":"Investigation (Purple)","stack":1,"percentage":30},{"itemId":753,"itemName":"비독룡의 억센발톱","iconName":"Fang","iconColor":"Orange","rank":"MR","source":"shiny","condition":"Shiny Drop","stack":1,"percentage":28},{"itemId":751,"itemName":"비독룡의 두툼모피","iconName":"Hide","iconColor":"Orange","rank":"MR","source":"questReward","condition":"Hunt (Bronze)","stack":1,"percentage":28},{"itemId":1089,"itemName":"영맥의 중용골","iconName":"Bone","iconColor":"Gray","rank":"MR","source":"guidingLands","condition":"Guiding Lands (Tempered)","stack":1,"percentage":25},{"itemId":751,"itemName":"비독룡의 두툼모피","iconName":"Hide","iconColor":"Orange","rank":"MR","source":"carve","condition":"Carve / Capture","stack":1,"percentage":24},{"itemId":752,"itemName":"비독룡의 두툼피막","iconName":"Wing","iconColor":"Orange","rank":"MR","source":"palico","condition":"Plunderblade","stack":1,"percentage":22},{"itemId":752,"itemName":"비독룡의 두툼피막","iconName":"Wing","iconColor":"Orange","rank":"MR","source":"questReward","condition":"Investigation (Silver)","stack":1,"percentage":22},{"itemId":607,"itemName":"용의 큰눈물방울","iconName":"Body","iconColor":"Blue","rank":"MR","source":"shiny","condition":"Shiny Drop","stack":1,"percentage":22},{"itemId":1090,"itemName":"영맥옥의 조각","iconName":"Streamstone","iconColor":"White","rank":"MR","source":"guidingLands","condition":"Guiding Lands (Tempered)","stack":1,"percentage":21},{"itemId":752,"itemName":"비독룡의 두툼피막","iconName":"Wing","iconColor":"Orange","rank":"MR","source":"carve","condition":"Carve / Capture","stack":1,"percentage":21},{"itemId":750,"itemName":"비독룡의 두툼비늘","iconName":"Scale","iconColor":"Orange","rank":"MR","source":"questReward","condition":"Hunt (Bronze)","stack":1,"percentage":21},{"itemId":751,"itemName":"비독룡의 두툼모피","iconName":"Hide","iconColor":"Orange","rank":"MR","source":"break","condition":"Wound Tail","stack":1,"percentage":20},{"itemId":750,"itemName":"비독룡의 두툼비늘","iconName":"Scale","iconColor":"Orange","rank":"MR","source":"break","condition":"Wound Back","stack":1,"percentage":20},{"itemId":753,"itemName":"비독룡의 억센발톱","iconName":"Fang","iconColor":"Orange","rank":"MR","source":"questReward","condition":"Investigation (Silver)","stack":1,"percentage":18},{"itemId":754,"itemName":"비독룡의 맹독침","iconName":"Body","iconColor":"Orange","rank":"MR","source":"questReward","condition":"Investigation (Gold)","stack":1,"percentage":18},{"itemId":752,"itemName":"비독룡의 두툼피막","iconName":"Wing","iconColor":"Orange","rank":"MR","source":"questReward","condition":"Investigation (Gold)","stack":1,"percentage":18},{"itemId":753,"itemName":"비독룡의 억센발톱","iconName":"Fang","iconColor":"Orange","rank":"MR","source":"questReward","condition":"Investigation (Gold)","stack":1,"percentage":18},{"itemId":752,"itemName":"비독룡의 두툼피막","iconName":"Wing","iconColor":"Orange","rank":"MR","source":"questReward","condition":"Hunt (Bronze)","stack":1,"percentage":17},{"itemId":790,"itemName":"대용옥","iconName":"Gem","iconColor":"Cyan","rank":"MR","source":"questReward","condition":"Investigation (Gold)","stack":1,"percentage":16},{"itemId":754,"itemName":"비독룡의 맹독침","iconName":"Body","iconColor":"Orange","rank":"MR","source":"questReward","condition":"Investigation (Silver)","stack":1,"percentage":16},{"itemId":754,"itemName":"비독룡의 맹독침","iconName":"Body","iconColor":"Orange","rank":"MR","source":"carve","condition":"Carve / Capture","stack":1,"percentage":12},{"itemId":751,"itemName":"비독룡의 두툼모피","iconName":"Hide","iconColor":"Orange","rank":"MR","source":"questReward","condition":"Investigation (Silver)","stack":2,"percentage":12},{"itemId":753,"itemName":"비독룡의 억센발톱","iconName":"Fang","iconColor":"Orange","rank":"MR","source":"questReward","condition":"Hunt (Bronze)","stack":1,"percentage":11},{"itemId":751,"itemName":"비독룡의 두툼모피","iconName":"Hide","iconColor":"Orange","rank":"MR","source":"questReward","condition":"Investigation (Gold)","stack":3,"percentage":10},{"itemId":750,"itemName":"비독룡의 두툼비늘","iconName":"Scale","iconColor":"Orange","rank":"MR","source":"questReward","condition":"Investigation (Silver)","stack":2,"percentage":10},{"itemId":699,"itemName":"농축 마비주머니","iconName":"Sac","iconColor":"Yellow","rank":"MR","source":"questReward","condition":"Hunt (Bronze)","stack":2,"percentage":10},{"itemId":698,"itemName":"극렬독주머니","iconName":"Sac","iconColor":"Violet","rank":"MR","source":"questReward","condition":"Hunt (Bronze)","stack":2,"percentage":10},{"itemId":753,"itemName":"비독룡의 억센발톱","iconName":"Fang","iconColor":"Orange","rank":"MR","source":"carve","condition":"Carve / Capture","stack":1,"percentage":10},{"itemId":790,"itemName":"대용옥","iconName":"Gem","iconColor":"Cyan","rank":"MR","source":"questReward","condition":"Investigation (Silver)","stack":1,"percentage":8},{"itemId":750,"itemName":"비독룡의 두툼비늘","iconName":"Scale","iconColor":"Orange","rank":"MR","source":"questReward","condition":"Investigation (Gold)","stack":3,"percentage":8},{"itemId":698,"itemName":"극렬독주머니","iconName":"Sac","iconColor":"Violet","rank":"MR","source":"questReward","condition":"Investigation (Silver)","stack":3,"percentage":7},{"itemId":699,"itemName":"농축 마비주머니","iconName":"Sac","iconColor":"Yellow","rank":"MR","source":"questReward","condition":"Investigation (Silver)","stack":3,"percentage":7},{"itemId":698,"itemName":"극렬독주머니","iconName":"Sac","iconColor":"Violet","rank":"MR","source":"questReward","condition":"Investigation (Gold)","stack":4,"percentage":6},{"itemId":699,"itemName":"농축 마비주머니","iconName":"Sac","iconColor":"Yellow","rank":"MR","source":"questReward","condition":"Investigation (Gold)","stack":4,"percentage":6},{"itemId":790,"itemName":"대용옥","iconName":"Gem","iconColor":"Cyan","rank":"MR","source":"carve","condition":"Carve / Capture","stack":1,"percentage":3},{"itemId":790,"itemName":"대용옥","iconName":"Gem","iconColor":"Cyan","rank":"MR","source":"questReward","condition":"Hunt (Bronze)","stack":1,"percentage":3},{"itemId":790,"itemName":"대용옥","iconName":"Gem","iconColor":"Cyan","rank":"MR","source":"palico","condition":"Plunderblade","stack":1,"percentage":2}]