[{"id":133,"name":"크샤나α","rank":"HR","bonus":{"name":"강룡의 비상","description":null,"skills":[{"name":"풍압 완전 무효","description":"모든 풍압을 무효화한다.","required":3,"levels":[{"level":1,"description":"모든 풍압을 무효화한다."}]}]},"pieces":[{"id":583,"name":"크샤나앵크α","type":"head","rarity":8,"defenseBase":64,"defenseMax":70,"defenseAugmentMax":84,"fire":0,"water":2,"thunder":-3,"ice":4,"dragon":-2,"slot1":0,"slot2":0,"slot3":0,"skills":[{"name":"얼음속성 공격 강화","description":"얼음속성의 힘을 강화한다. (무기의 속성치 강화에는 한계가 있습니다)","level":2,"levels":[{"level":1,"description":"얼음속성 공격치＋30"},{"level":2,"description":"얼음속성 공격치＋60"},{"level":3,"description":"얼음속성 공격치＋100"},{"level":4,"description":"얼음속성 공격치가 1.05배가 되고 얼음속성 공격치에＋100"},{"level":5,"description":"얼음속성 공격치가 1.1배가 되고 얼음속성 공격치에＋100"},{"level":6,"description":"얼음속성 공격치가 1.2배가 되고 얼음속성 공격치에＋100"}]},{"name":"장인","description":"무기의 예리도 게이지가 늘어난다. 단, 예리도 게이지의 한계 이상으로 늘어나지는 않는다.","level":1,"levels":[{"level":1,"description":"무기의 예리도＋10"},{"level":2,"description":"무기의 예리도＋20"},{"level":3,"description":"무기의 예리도＋30"},{"level":4,"description":"무기의 예리도＋40"},{"level":5,"description":"무기의 예리도＋50"}]}],"materials":[{"itemId":152,"name":"고룡골","quantity":4},{"itemId":443,"name":"강철의 용비늘+","quantity":4},{"itemId":444,"name":"강룡의 견갑각","quantity":4},{"itemId":445,"name":"강룡의 날개","quantity":2}]},{"id":584,"name":"크샤나딜α","type":"chest","rarity":8,"defenseBase":64,"defenseMax":70,"defenseAugmentMax":84,"fire":0,"water":2,"thunder":-3,"ice":4,"dragon":-2,"slot1":0,"slot2":0,"slot3":0,"skills":[{"name":"장인","description":"무기의 예리도 게이지가 늘어난다. 단, 예리도 게이지의 한계 이상으로 늘어나지는 않는다.","level":2,"levels":[{"level":1,"description":"무기의 예리도＋10"},{"level":2,"description":"무기의 예리도＋20"},{"level":3,"description":"무기의 예리도＋30"},{"level":4,"description":"무기의 예리도＋40"},{"level":5,"description":"무기의 예리도＋50"}]},{"name":"집중","description":"태도, 쌍검, 슬래시액스, 차지액스의 게이지와 대검, 해머, 활의 모으기 속도가 빨라진다.","level":1,"levels":[{"level":1,"description":"게이지 상승률 5％ UP 모으기 시간 5％ 단축"},{"level":2,"description":"게이지 상승률 10％ UP 모으기 시간 10％ 단축"},{"level":3,"description":"게이지 상승률 20％ UP 모으기 시간 15％ 단축"}]}],"materials":[{"itemId":444,"name":"강룡의 견갑각","quantity":5},{"itemId":446,"name":"강룡의 첨예뿔","quantity":3},{"itemId":448,"name":"강룡의 첨예발톱","quantity":2},{"itemId":449,"name":"강룡의 보옥","quantity":1}]},{"id":585,"name":"크샤나하투α","type":"arms","rarity":8,"defenseBase":64,"defenseMax":70,"defenseAugmentMax":84,"fire":0,"water":2,"thunder":-3,"ice":4,"dragon":-2,"slot1":0,"slot2":0,"slot3":0,"skills":[{"name":"회피 성능","description":"회피 시 무적 시간이 늘어난다.","level":2,"levels":[{"level":1,"description":"무적 시간이 아주 조금 연장."},{"level":2,"description":"무적 시간이 조금 연장."},{"level":3,"description":"무적 시간이 연장."},{"level":4,"description":"무적 시간이 크게 연장."},{"level":5,"description":"무적 시간이 매우 크게 연장."}]},{"name":"장인","description":"무기의 예리도 게이지가 늘어난다. 단, 예리도 게이지의 한계 이상으로 늘어나지는 않는다.","level":1,"levels":[{"level":1,"description":"무기의 예리도＋10"},{"level":2,"description":"무기의 예리도＋20"},{"level":3,"description":"무기의 예리도＋30"},{"level":4,"description":"무기의 예리도＋40"},{"level":5,"description":"무기의 예리도＋50"}]}],"materials":[{"itemId":322,"name":"풍표룡의 역린","quantity":1},{"itemId":444,"name":"강룡의 견갑각","quantity":5},{"itemId":446,"name":"강룡의 첨예뿔","quantity":2},{"itemId":447,"name":"강룡의 꼬리","quantity":2}]},{"id":586,"name":"크샤나안다α","type":"waist","rarity":8,"defenseBase":64,"defenseMax":70,"defenseAugmentMax":84,"fire":0,"water":2,"thunder":-3,"ice":4,"dragon":-2,"slot1":0,"slot2":0,"slot3":0,"skills":[{"name":"얼음속성 공격 강화","description":"얼음속성의 힘을 강화한다. (무기의 속성치 강화에는 한계가 있습니다)","level":2,"levels":[{"level":1,"description":"얼음속성 공격치＋30"},{"level":2,"description":"얼음속성 공격치＋60"},{"level":3,"description":"얼음속성 공격치＋100"},{"level":4,"description":"얼음속성 공격치가 1.05배가 되고 얼음속성 공격치에＋100"},{"level":5,"description":"얼음속성 공격치가 1.1배가 되고 얼음속성 공격치에＋100"},{"level":6,"description":"얼음속성 공격치가 1.2배가 되고 얼음속성 공격치에＋100"}]},{"name":"회피 거리 UP","description":"회피 시의 이동 거리가 길어진다.","level":1,"levels":[{"level":1,"description":"회피 거리가 조금 연장."},{"level":2,"description":"회피 거리가 연장."},{"level":3,"description":"회피 거리가 크게 연장."}]}],"materials":[{"itemId":118,"name":"카브레라이트광석","quantity":5},{"itemId":443,"name":"강철의 용비늘+","quantity":4},{"itemId":444,"name":"강룡의 견갑각","quantity":4},{"itemId":446,"name":"강룡의 첨예뿔","quantity":2}]},{"id":587,"name":"크샤나페이르α","type":"legs","rarity":8,"defenseBase":64,"defenseMax":70,"defenseAugmentMax":84,"fire":0,"water":2,"thunder":-3,"ice":4,"dragon":-2,"slot1":0,"slot2":0,"slot3":0,"skills":[{"name":"회피 거리 UP","description":"회피 시의 이동 거리가 길어진다.","level":2,"levels":[{"level":1,"description":"회피 거리가 조금 연장."},{"level":2,"description":"회피 거리가 연장."},{"level":3,"description":"회피 거리가 크게 연장."}]},{"name":"장인","description":"무기의 예리도 게이지가 늘어난다. 단, 예리도 게이지의 한계 이상으로 늘어나지는 않는다.","level":1,"levels":[{"level":1,"description":"무기의 예리도＋10"},{"level":2,"description":"무기의 예리도＋20"},{"level":3,"description":"무기의 예리도＋30"},{"level":4,"description":"무기의 예리도＋40"},{"level":5,"description":"무기의 예리도＋50"}]}],"materials":[{"itemId":173,"name":"고룡의 피","quantity":3},{"itemId":443,"name":"강철의 용비늘+","quantity":4},{"itemId":444,"name":"강룡의 견갑각","quantity":5},{"itemId":445,"name":"강룡의 날개","quantity":3}]}]},{"id":134,"name":"크샤나β","rank":"HR","bonus":{"name":"강룡의 비상","description":null,"skills":[{"name":"풍압 완전 무효","description":"모든 풍압을 무효화한다.","required":3,"levels":[{"level":1,"description":"모든 풍압을 무효화한다."}]}]},"pieces":[{"id":588,"name":"크샤나앵크β","type":"head","rarity":8,"defenseBase":64,"defenseMax":70,"defenseAugmentMax":84,"fire":0,"water":2,"thunder":-3,"ice":4,"dragon":-2,"slot1":1,"slot2":1,"slot3":1,"skills":[{"name":"얼음속성 공격 강화","description":"얼음속성의 힘을 강화한다. (무기의 속성치 강화에는 한계가 있습니다)","level":2,"levels":[{"level":1,"description":"얼음속성 공격치＋30"},{"level":2,"description":"얼음속성 공격치＋60"},{"level":3,"description":"얼음속성 공격치＋100"},{"level":4,"description":"얼음속성 공격치가 1.05배가 되고 얼음속성 공격치에＋100"},{"level":5,"description":"얼음속성 공격치가 1.1배가 되고 얼음속성 공격치에＋100"},{"level":6,"description":"얼음속성 공격치가 1.2배가 되고 얼음속성 공격치에＋100"}]}],"materials":[{"itemId":152,"name":"고룡골","quantity":4},{"itemId":443,"name":"강철의 용비늘+","quantity":4},{"itemId":444,"name":"강룡의 견갑각","quantity":4},{"itemId":445,"name":"강룡의 날개","quantity":2}]},{"id":589,"name":"크샤나딜β","type":"chest","rarity":8,"defenseBase":64,"defenseMax":70,"defenseAugmentMax":84,"fire":0,"water":2,"thunder":-3,"ice":4,"dragon":-2,"slot1":2,"slot2":0,"slot3":0,"skills":[{"name":"장인","description":"무기의 예리도 게이지가 늘어난다. 단, 예리도 게이지의 한계 이상으로 늘어나지는 않는다.","level":2,"levels":[{"level":1,"description":"무기의 예리도＋10"},{"level":2,"description":"무기의 예리도＋20"},{"level":3,"description":"무기의 예리도＋30"},{"level":4,"description":"무기의 예리도＋40"},{"level":5,"description":"무기의 예리도＋50"}]}],"materials":[{"itemId":444,"name":"강룡의 견갑각","quantity":5},{"itemId":446,"name":"강룡의 첨예뿔","quantity":3},{"itemId":448,"name":"강룡의 첨예발톱","quantity":2},{"itemId":449,"name":"강룡의 보옥","quantity":1}]},{"id":590,"name":"크샤나하투β","type":"arms","rarity":8,"defenseBase":64,"defenseMax":70,"defenseAugmentMax":84,"fire":0,"water":2,"thunder":-3,"ice":4,"dragon":-2,"slot1":3,"slot2":0,"slot3":0,"skills":[{"name":"회피 성능","description":"회피 시 무적 시간이 늘어난다.","level":2,"levels":[{"level":1,"description":"무적 시간이 아주 조금 연장."},{"level":2,"description":"무적 시간이 조금 연장."},{"level":3,"description":"무적 시간이 연장."},{"level":4,"description":"무적 시간이 크게 연장."},{"level":5,"description":"무적 시간이 매우 크게 연장."}]}],"materials":[{"itemId":322,"name":"풍표룡의 역린","quantity":1},{"itemId":444,"name":"강룡의 견갑각","quantity":5},{"itemId":446,"name":"강룡의 첨예뿔","quantity":2},{"itemId":447,"name":"강룡의 꼬리","quantity":2}]},{"id":591,"name":"크샤나안다β","type":"waist","rarity":8,"defenseBase":64,"defenseMax":70,"defenseAugmentMax":84,"fire":0,"water":2,"thunder":-3,"ice":4,"dragon":-2,"slot1":1,"slot2":1,"slot3":0,"skills":[{"name":"얼음속성 공격 강화","description":"얼음속성의 힘을 강화한다. (무기의 속성치 강화에는 한계가 있습니다)","level":2,"levels":[{"level":1,"description":"얼음속성 공격치＋30"},{"level":2,"description":"얼음속성 공격치＋60"},{"level":3,"description":"얼음속성 공격치＋100"},{"level":4,"description":"얼음속성 공격치가 1.05배가 되고 얼음속성 공격치에＋100"},{"level":5,"description":"얼음속성 공격치가 1.1배가 되고 얼음속성 공격치에＋100"},{"level":6,"description":"얼음속성 공격치가 1.2배가 되고 얼음속성 공격치에＋100"}]}],"materials":[{"itemId":118,"name":"카브레라이트광석","quantity":5},{"itemId":443,"name":"강철의 용비늘+","quantity":4},{"itemId":444,"name":"강룡의 견갑각","quantity":4},{"itemId":446,"name":"강룡의 첨예뿔","quantity":2}]},{"id":592,"name":"크샤나페이르β","type":"legs","rarity":8,"defenseBase":64,"defenseMax":70,"defenseAugmentMax":84,"fire":0,"water":2,"thunder":-3,"ice":4,"dragon":-2,"slot1":3,"slot2":0,"slot3":0,"skills":[{"name":"회피 거리 UP","description":"회피 시의 이동 거리가 길어진다.","level":2,"levels":[{"level":1,"description":"회피 거리가 조금 연장."},{"level":2,"description":"회피 거리가 연장."},{"level":3,"description":"회피 거리가 크게 연장."}]}],"materials":[{"itemId":173,"name":"고룡의 피","quantity":3},{"itemId":443,"name":"강철의 용비늘+","quantity":4},{"itemId":444,"name":"강룡의 견갑각","quantity":5},{"itemId":445,"name":"강룡의 날개","quantity":3}]}]},{"id":162,"name":"크샤나γ","rank":"HR","bonus":{"name":"강룡의 비상","description":null,"skills":[{"name":"풍압 완전 무효","description":"모든 풍압을 무효화한다.","required":3,"levels":[{"level":1,"description":"모든 풍압을 무효화한다."}]}]},"pieces":[{"id":753,"name":"크샤나앵크γ","type":"head","rarity":8,"defenseBase":72,"defenseMax":78,"defenseAugmentMax":92,"fire":0,"water":2,"thunder":-3,"ice":4,"dragon":-2,"slot1":2,"slot2":0,"slot3":0,"skills":[{"name":"장인","description":"무기의 예리도 게이지가 늘어난다. 단, 예리도 게이지의 한계 이상으로 늘어나지는 않는다.","level":2,"levels":[{"level":1,"description":"무기의 예리도＋10"},{"level":2,"description":"무기의 예리도＋20"},{"level":3,"description":"무기의 예리도＋30"},{"level":4,"description":"무기의 예리도＋40"},{"level":5,"description":"무기의 예리도＋50"}]}],"materials":[{"itemId":444,"name":"강룡의 견갑각","quantity":5},{"itemId":446,"name":"강룡의 첨예뿔","quantity":3},{"itemId":449,"name":"강룡의 보옥","quantity":1},{"itemId":656,"name":"강룡 티켓","quantity":1}]},{"id":754,"name":"크샤나딜γ","type":"chest","rarity":8,"defenseBase":72,"defenseMax":78,"defenseAugmentMax":92,"fire":0,"water":2,"thunder":-3,"ice":4,"dragon":-2,"slot1":2,"slot2":0,"slot3":0,"skills":[{"name":"얼음속성 공격 강화","description":"얼음속성의 힘을 강화한다. (무기의 속성치 강화에는 한계가 있습니다)","level":3,"levels":[{"level":1,"description":"얼음속성 공격치＋30"},{"level":2,"description":"얼음속성 공격치＋60"},{"level":3,"description":"얼음속성 공격치＋100"},{"level":4,"description":"얼음속성 공격치가 1.05배가 되고 얼음속성 공격치에＋100"},{"level":5,"description":"얼음속성 공격치가 1.1배가 되고 얼음속성 공격치에＋100"},{"level":6,"description":"얼음속성 공격치가 1.2배가 되고 얼음속성 공격치에＋100"}]},{"name":"회피 거리 UP","description":"회피 시의 이동 거리가 길어진다.","level":1,"levels":[{"level":1,"description":"회피 거리가 조금 연장."},{"level":2,"description":"회피 거리가 연장."},{"level":3,"description":"회피 거리가 크게 연장."}]}],"materials":[{"itemId":443,"name":"강철의 용비늘+","quantity":4},{"itemId":444,"name":"강룡의 견갑각","quantity":4},{"itemId":445,"name":"강룡의 날개","quantity":2},{"itemId":656,"name":"강룡 티켓","quantity":1}]},{"id":755,"name":"크샤나하투γ","type":"arms","rarity":8,"defenseBase":72,"defenseMax":78,"defenseAugmentMax":92,"fire":0,"water":2,"thunder":-3,"ice":4,"dragon":-2,"slot1":1,"slot2":1,"slot3":1,"skills":[{"name":"집중","description":"태도, 쌍검, 슬래시액스, 차지액스의 게이지와 대검, 해머, 활의 모으기 속도가 빨라진다.","level":2,"levels":[{"level":1,"description":"게이지 상승률 5％ UP 모으기 시간 5％ 단축"},{"level":2,"description":"게이지 상승률 10％ UP 모으기 시간 10％ 단축"},{"level":3,"description":"게이지 상승률 20％ UP 모으기 시간 15％ 단축"}]}],"materials":[{"itemId":443,"name":"강철의 용비늘+","quantity":4},{"itemId":444,"name":"강룡의 견갑각","quantity":4},{"itemId":448,"name":"강룡의 첨예발톱","quantity":2},{"itemId":656,"name":"강룡 티켓","quantity":1}]},{"id":756,"name":"크샤나안다γ","type":"waist","rarity":8,"defenseBase":72,"defenseMax":78,"defenseAugmentMax":92,"fire":0,"water":2,"thunder":-3,"ice":4,"dragon":-2,"slot1":1,"slot2":1,"slot3":0,"skills":[{"name":"장인","description":"무기의 예리도 게이지가 늘어난다. 단, 예리도 게이지의 한계 이상으로 늘어나지는 않는다.","level":2,"levels":[{"level":1,"description":"무기의 예리도＋10"},{"level":2,"description":"무기의 예리도＋20"},{"level":3,"description":"무기의 예리도＋30"},{"level":4,"description":"무기의 예리도＋40"},{"level":5,"description":"무기의 예리도＋50"}]}],"materials":[{"itemId":443,"name":"강철의 용비늘+","quantity":4},{"itemId":444,"name":"강룡의 견갑각","quantity":5},{"itemId":445,"name":"강룡의 날개","quantity":3},{"itemId":656,"name":"강룡 티켓","quantity":1}]},{"id":757,"name":"크샤나페이르γ","type":"legs","rarity":8,"defenseBase":72,"defenseMax":78,"defenseAugmentMax":92,"fire":0,"water":2,"thunder":-3,"ice":4,"dragon":-2,"slot1":3,"slot2":0,"slot3":0,"skills":[{"name":"회피 성능","description":"회피 시 무적 시간이 늘어난다.","level":2,"levels":[{"level":1,"description":"무적 시간이 아주 조금 연장."},{"level":2,"description":"무적 시간이 조금 연장."},{"level":3,"description":"무적 시간이 연장."},{"level":4,"description":"무적 시간이 크게 연장."},{"level":5,"description":"무적 시간이 매우 크게 연장."}]}],"materials":[{"itemId":444,"name":"강룡의 견갑각","quantity":5},{"itemId":446,"name":"강룡의 첨예뿔","quantity":2},{"itemId":447,"name":"강룡의 꼬리","quantity":2},{"itemId":656,"name":"강룡 티켓","quantity":1}]}]},{"id":295,"name":"EX크샤나α","rank":"MR","bonus":{"name":"강룡의 비상","description":null,"skills":[{"name":"풍압 완전 무효","description":"모든 풍압을 무효화한다.","required":3,"levels":[{"level":1,"description":"모든 풍압을 무효화한다."}]}]},"pieces":[{"id":1327,"name":"EX크샤나앵크α","type":"head","rarity":12,"defenseBase":156,"defenseMax":174,"defenseAugmentMax":194,"fire":0,"water":2,"thunder":-3,"ice":4,"dragon":-2,"slot1":2,"slot2":0,"slot3":0,"skills":[{"name":"얼음속성 공격 강화","description":"얼음속성의 힘을 강화한다. (무기의 속성치 강화에는 한계가 있습니다)","level":2,"levels":[{"level":1,"description":"얼음속성 공격치＋30"},{"level":2,"description":"얼음속성 공격치＋60"},{"level":3,"description":"얼음속성 공격치＋100"},{"level":4,"description":"얼음속성 공격치가 1.05배가 되고 얼음속성 공격치에＋100"},{"level":5,"description":"얼음속성 공격치가 1.1배가 되고 얼음속성 공격치에＋100"},{"level":6,"description":"얼음속성 공격치가 1.2배가 되고 얼음속성 공격치에＋100"}]},{"name":"회피 성능","description":"회피 시 무적 시간이 늘어난다.","level":2,"levels":[{"level":1,"description":"무적 시간이 아주 조금 연장."},{"level":2,"description":"무적 시간이 조금 연장."},{"level":3,"description":"무적 시간이 연장."},{"level":4,"description":"무적 시간이 크게 연장."},{"level":5,"description":"무적 시간이 매우 크게 연장."}]}],"materials":[{"itemId":790,"name":"대용옥","quantity":1},{"itemId":973,"name":"강룡의 중갑각","quantity":4},{"itemId":974,"name":"강철의 두툼용비늘","quantity":3},{"itemId":978,"name":"강룡의 억센발톱","quantity":1}]},{"id":1328,"name":"EX크샤나딜α","type":"chest","rarity":12,"defenseBase":156,"defenseMax":174,"defenseAugmentMax":194,"fire":0,"water":2,"thunder":-3,"ice":4,"dragon":-2,"slot1":1,"slot2":0,"slot3":0,"skills":[{"name":"장인","description":"무기의 예리도 게이지가 늘어난다. 단, 예리도 게이지의 한계 이상으로 늘어나지는 않는다.","level":3,"levels":[{"level":1,"description":"무기의 예리도＋10"},{"level":2,"description":"무기의 예리도＋20"},{"level":3,"description":"무기의 예리도＋30"},{"level":4,"description":"무기의 예리도＋40"},{"level":5,"description":"무기의 예리도＋50"}]}],"materials":[{"itemId":791,"name":"고룡의 깨끗한 피","quantity":6},{"itemId":973,"name":"강룡의 중갑각","quantity":4},{"itemId":975,"name":"강룡의 억센날개","quantity":3},{"itemId":977,"name":"강룡의 질긴꼬리","quantity":2}]},{"id":1329,"name":"EX크샤나하투α","type":"arms","rarity":12,"defenseBase":156,"defenseMax":174,"defenseAugmentMax":194,"fire":0,"water":2,"thunder":-3,"ice":4,"dragon":-2,"slot1":1,"slot2":0,"slot3":0,"skills":[{"name":"회피 성능","description":"회피 시 무적 시간이 늘어난다.","level":3,"levels":[{"level":1,"description":"무적 시간이 아주 조금 연장."},{"level":2,"description":"무적 시간이 조금 연장."},{"level":3,"description":"무적 시간이 연장."},{"level":4,"description":"무적 시간이 크게 연장."},{"level":5,"description":"무적 시간이 매우 크게 연장."}]}],"materials":[{"itemId":792,"name":"고룡의 대보옥","quantity":1},{"itemId":973,"name":"강룡의 중갑각","quantity":4},{"itemId":975,"name":"강룡의 억센날개","quantity":3},{"itemId":976,"name":"강룡의 억센뿔","quantity":2}]},{"id":1330,"name":"EX크샤나안다α","type":"waist","rarity":12,"defenseBase":156,"defenseMax":174,"defenseAugmentMax":194,"fire":0,"water":2,"thunder":-3,"ice":4,"dragon":-2,"slot1":2,"slot2":0,"slot3":0,"skills":[{"name":"얼음속성 공격 강화","description":"얼음속성의 힘을 강화한다. (무기의 속성치 강화에는 한계가 있습니다)","level":3,"levels":[{"level":1,"description":"얼음속성 공격치＋30"},{"level":2,"description":"얼음속성 공격치＋60"},{"level":3,"description":"얼음속성 공격치＋100"},{"level":4,"description":"얼음속성 공격치가 1.05배가 되고 얼음속성 공격치에＋100"},{"level":5,"description":"얼음속성 공격치가 1.1배가 되고 얼음속성 공격치에＋100"},{"level":6,"description":"얼음속성 공격치가 1.2배가 되고 얼음속성 공격치에＋100"}]},{"name":"회피 거리 UP","description":"회피 시의 이동 거리가 길어진다.","level":1,"levels":[{"level":1,"description":"회피 거리가 조금 연장."},{"level":2,"description":"회피 거리가 연장."},{"level":3,"description":"회피 거리가 크게 연장."}]}],"materials":[{"itemId":875,"name":"호박색 중어금니","quantity":3},{"itemId":973,"name":"강룡의 중갑각","quantity":4},{"itemId":974,"name":"강철의 두툼용비늘","quantity":3},{"itemId":976,"name":"강룡의 억센뿔","quantity":1}]},{"id":1331,"name":"EX크샤나페이르α","type":"legs","rarity":12,"defenseBase":156,"defenseMax":174,"defenseAugmentMax":194,"fire":0,"water":2,"thunder":-3,"ice":4,"dragon":-2,"slot1":1,"slot2":0,"slot3":0,"skills":[{"name":"회피 거리 UP","description":"회피 시의 이동 거리가 길어진다.","level":2,"levels":[{"level":1,"description":"회피 거리가 조금 연장."},{"level":2,"description":"회피 거리가 연장."},{"level":3,"description":"회피 거리가 크게 연장."}]},{"name":"장인","description":"무기의 예리도 게이지가 늘어난다. 단, 예리도 게이지의 한계 이상으로 늘어나지는 않는다.","level":2,"levels":[{"level":1,"description":"무기의 예리도＋10"},{"level":2,"description":"무기의 예리도＋20"},{"level":3,"description":"무기의 예리도＋30"},{"level":4,"description":"무기의 예리도＋40"},{"level":5,"description":"무기의 예리도＋50"}]}],"materials":[{"itemId":882,"name":"신룡의 하늘비늘","quantity":1},{"itemId":973,"name":"강룡의 중갑각","quantity":4},{"itemId":977,"name":"강룡의 질긴꼬리","quantity":1},{"itemId":978,"name":"강룡의 억센발톱","quantity":2}]}]},{"id":296,"name":"EX크샤나β","rank":"MR","bonus":{"name":"강룡의 비상","description":null,"skills":[{"name":"풍압 완전 무효","description":"모든 풍압을 무효화한다.","required":3,"levels":[{"level":1,"description":"모든 풍압을 무효화한다."}]}]},"pieces":[{"id":1332,"name":"EX크샤나앵크β","type":"head","rarity":12,"defenseBase":156,"defenseMax":174,"defenseAugmentMax":194,"fire":0,"water":2,"thunder":-3,"ice":4,"dragon":-2,"slot1":4,"slot2":1,"slot3":0,"skills":[{"name":"얼음속성 공격 강화","description":"얼음속성의 힘을 강화한다. (무기의 속성치 강화에는 한계가 있습니다)","level":2,"levels":[{"level":1,"description":"얼음속성 공격치＋30"},{"level":2,"description":"얼음속성 공격치＋60"},{"level":3,"description":"얼음속성 공격치＋100"},{"level":4,"description":"얼음속성 공격치가 1.05배가 되고 얼음속성 공격치에＋100"},{"level":5,"description":"얼음속성 공격치가 1.1배가 되고 얼음속성 공격치에＋100"},{"level":6,"description":"얼음속성 공격치가 1.2배가 되고 얼음속성 공격치에＋100"}]},{"name":"회피 성능","description":"회피 시 무적 시간이 늘어난다.","level":1,"levels":[{"level":1,"description":"무적 시간이 아주 조금 연장."},{"level":2,"description":"무적 시간이 조금 연장."},{"level":3,"description":"무적 시간이 연장."},{"level":4,"description":"무적 시간이 크게 연장."},{"level":5,"description":"무적 시간이 매우 크게 연장."}]}],"materials":[{"itemId":790,"name":"대용옥","quantity":1},{"itemId":973,"name":"강룡의 중갑각","quantity":4},{"itemId":974,"name":"강철의 두툼용비늘","quantity":3},{"itemId":978,"name":"강룡의 억센발톱","quantity":1}]},{"id":1333,"name":"EX크샤나딜β","type":"chest","rarity":12,"defenseBase":156,"defenseMax":174,"defenseAugmentMax":194,"fire":0,"water":2,"thunder":-3,"ice":4,"dragon":-2,"slot1":4,"slot2":2,"slot3":0,"skills":[{"name":"장인","description":"무기의 예리도 게이지가 늘어난다. 단, 예리도 게이지의 한계 이상으로 늘어나지는 않는다.","level":2,"levels":[{"level":1,"description":"무기의 예리도＋10"},{"level":2,"description":"무기의 예리도＋20"},{"level":3,"description":"무기의 예리도＋30"},{"level":4,"description":"무기의 예리도＋40"},{"level":5,"description":"무기의 예리도＋50"}]}],"materials":[{"itemId":791,"name":"고룡의 깨끗한 피","quantity":6},{"itemId":973,"name":"강룡의 중갑각","quantity":4},{"itemId":975,"name":"강룡의 억센날개","quantity":3},{"itemId":977,"name":"강룡의 질긴꼬리","quantity":2}]},{"id":1334,"name":"EX크샤나하투β","type":"arms","rarity":12,"defenseBase":156,"defenseMax":174,"defenseAugmentMax":194,"fire":0,"water":2,"thunder":-3,"ice":4,"dragon":-2,"slot1":4,"slot2":2,"slot3":0,"skills":[{"name":"회피 성능","description":"회피 시 무적 시간이 늘어난다.","level":2,"levels":[{"level":1,"description":"무적 시간이 아주 조금 연장."},{"level":2,"description":"무적 시간이 조금 연장."},{"level":3,"description":"무적 시간이 연장."},{"level":4,"description":"무적 시간이 크게 연장."},{"level":5,"description":"무적 시간이 매우 크게 연장."}]}],"materials":[{"itemId":792,"name":"고룡의 대보옥","quantity":1},{"itemId":973,"name":"강룡의 중갑각","quantity":4},{"itemId":975,"name":"강룡의 억센날개","quantity":3},{"itemId":976,"name":"강룡의 억센뿔","quantity":2}]},{"id":1335,"name":"EX크샤나안다β","type":"waist","rarity":12,"defenseBase":156,"defenseMax":174,"defenseAugmentMax":194,"fire":0,"water":2,"thunder":-3,"ice":4,"dragon":-2,"slot1":4,"slot2":1,"slot3":0,"skills":[{"name":"얼음속성 공격 강화","description":"얼음속성의 힘을 강화한다. (무기의 속성치 강화에는 한계가 있습니다)","level":3,"levels":[{"level":1,"description":"얼음속성 공격치＋30"},{"level":2,"description":"얼음속성 공격치＋60"},{"level":3,"description":"얼음속성 공격치＋100"},{"level":4,"description":"얼음속성 공격치가 1.05배가 되고 얼음속성 공격치에＋100"},{"level":5,"description":"얼음속성 공격치가 1.1배가 되고 얼음속성 공격치에＋100"},{"level":6,"description":"얼음속성 공격치가 1.2배가 되고 얼음속성 공격치에＋100"}]}],"materials":[{"itemId":875,"name":"호박색 중어금니","quantity":3},{"itemId":973,"name":"강룡의 중갑각","quantity":4},{"itemId":974,"name":"강철의 두툼용비늘","quantity":3},{"itemId":976,"name":"강룡의 억센뿔","quantity":1}]},{"id":1336,"name":"EX크샤나페이르β","type":"legs","rarity":12,"defenseBase":156,"defenseMax":174,"defenseAugmentMax":194,"fire":0,"water":2,"thunder":-3,"ice":4,"dragon":-2,"slot1":4,"slot2":3,"slot3":0,"skills":[{"name":"회피 거리 UP","description":"회피 시의 이동 거리가 길어진다.","level":2,"levels":[{"level":1,"description":"회피 거리가 조금 연장."},{"level":2,"description":"회피 거리가 연장."},{"level":3,"description":"회피 거리가 크게 연장."}]}],"materials":[{"itemId":882,"name":"신룡의 하늘비늘","quantity":1},{"itemId":973,"name":"강룡의 중갑각","quantity":4},{"itemId":977,"name":"강룡의 질긴꼬리","quantity":1},{"itemId":978,"name":"강룡의 억센발톱","quantity":2}]}]}]